LICENSE
ionic_haystack/__init__.py
ionic_haystack/prompt_templates.py
ionic_haystack/tool.py
ionic_haystack-0.1.6.dist-info/LICENSE
ionic_haystack-0.1.6.dist-info/METADATA
ionic_haystack-0.1.6.dist-info/WHEEL
ionic_haystack-0.1.6.dist-info/RECORD
