Metadata-Version: 2.1
Name: ionic-haystack
Version: 0.1.6
Summary: Ionic Commerce tool for Haystack
Author: Your Name
Author-email: you@example.com
Requires-Python: >=3.8,<4.0
Classifier: Programming Language :: Python :: 3
Classifier: Programming Language :: Python :: 3.8
Classifier: Programming Language :: Python :: 3.9
Classifier: Programming Language :: Python :: 3.10
Classifier: Programming Language :: Python :: 3.11
Classifier: Programming Language :: Python :: 3.12
Requires-Dist: Ionic-API-SDK (>=0.7.1,<0.8.0)
Requires-Dist: farm-haystack[colab] (>=1.24.0,<2.0.0)
